{"chemical-plant":{"picture":{"west":{"layers":[{"x":0,"y":888,"hr_version":{"x":0,"y":1752,"height":292,"filename":"__base__/graphics/entity/chemical-plant/hr-chemical-plant.png","frame_count":24,"priority":"high","scale":0.5,"shift":[0.015625,-0.28125],"line_length":12,"width":220},"height":148,"filename":"__base__/graphics/entity/chemical-plant/chemical-plant.png","frame_count":24,"priority":"high","scale":1,"shift":[0.03125,-0.28125],"line_length":12,"width":108},{"x":462,"y":0,"hr_version":{"x":936,"y":0,"height":222,"filename":"__base__/graphics/entity/chemical-plant/hr-chemical-plant-shadow.png","frame_count":1,"priority":"high","repeat_count":24,"scale":0.5,"draw_as_shadow":true,"shift":[0.84375,0.1875],"width":312},"height":112,"filename":"__base__/graphics/entity/chemical-plant/chemical-plant-shadow.png","frame_count":1,"priority":"high","repeat_count":24,"scale":1,"draw_as_shadow":true,"shift":[0.875,0.1875],"width":154}]},"north":{"layers":[{"x":0,"y":0,"hr_version":{"x":0,"y":0,"height":292,"filename":"__base__/graphics/entity/chemical-plant/hr-chemical-plant.png","frame_count":24,"priority":"high","scale":0.5,"shift":[0.015625,-0.28125],"line_length":12,"width":220},"height":148,"filename":"__base__/graphics/entity/chemical-plant/chemical-plant.png","frame_count":24,"priority":"high","scale":1,"shift":[0.03125,-0.28125],"line_length":12,"width":108},{"x":0,"y":0,"hr_version":{"x":0,"y":0,"height":222,"filename":"__base__/graphics/entity/chemical-plant/hr-chemical-plant-shadow.png","frame_count":1,"priority":"high","repeat_count":24,"scale":0.5,"draw_as_shadow":true,"shift":[0.84375,0.1875],"width":312},"height":112,"filename":"__base__/graphics/entity/chemical-plant/chemical-plant-shadow.png","frame_count":1,"priority":"high","repeat_count":24,"scale":1,"draw_as_shadow":true,"shift":[0.875,0.1875],"width":154}]},"east":{"layers":[{"x":0,"y":296,"hr_version":{"x":0,"y":584,"height":292,"filename":"__base__/graphics/entity/chemical-plant/hr-chemical-plant.png","frame_count":24,"priority":"high","scale":0.5,"shift":[0.015625,-0.28125],"line_length":12,"width":220},"height":148,"filename":"__base__/graphics/entity/chemical-plant/chemical-plant.png","frame_count":24,"priority":"high","scale":1,"shift":[0.03125,-0.28125],"line_length":12,"width":108},{"x":154,"y":0,"hr_version":{"x":312,"y":0,"height":222,"filename":"__base__/graphics/entity/chemical-plant/hr-chemical-plant-shadow.png","frame_count":1,"priority":"high","repeat_count":24,"scale":0.5,"draw_as_shadow":true,"shift":[0.84375,0.1875],"width":312},"height":112,"filename":"__base__/graphics/entity/chemical-plant/chemical-plant-shadow.png","frame_count":1,"priority":"high","repeat_count":24,"scale":1,"draw_as_shadow":true,"shift":[0.875,0.1875],"width":154}]},"south":{"layers":[{"x":0,"y":592,"hr_version":{"x":0,"y":1168,"height":292,"filename":"__base__/graphics/entity/chemical-plant/hr-chemical-plant.png","frame_count":24,"priority":"high","scale":0.5,"shift":[0.015625,-0.28125],"line_length":12,"width":220},"height":148,"filename":"__base__/graphics/entity/chemical-plant/chemical-plant.png","frame_count":24,"priority":"high","scale":1,"shift":[0.03125,-0.28125],"line_length":12,"width":108},{"x":308,"y":0,"hr_version":{"x":624,"y":0,"height":222,"filename":"__base__/graphics/entity/chemical-plant/hr-chemical-plant-shadow.png","frame_count":1,"priority":"high","repeat_count":24,"scale":0.5,"draw_as_shadow":true,"shift":[0.84375,0.1875],"width":312},"height":112,"filename":"__base__/graphics/entity/chemical-plant/chemical-plant-shadow.png","frame_count":1,"priority":"high","repeat_count":24,"scale":1,"draw_as_shadow":true,"shift":[0.875,0.1875],"width":154}]}}},"offshore-pump":{"picture":{"west":{"layers":[{"line_length":8,"hr_version":{"line_length":8,"frame_count":32,"priority":"high","filename":"__base__/graphics/entity/offshore-pump/hr-offshore-pump_West.png","scale":0.5,"shift":[-0.46875,-0.0625],"height":102,"width":124,"animation_speed":0.25},"frame_count":32,"priority":"high","filename":"__base__/graphics/entity/offshore-pump/offshore-pump_West.png","shift":[-0.5,-0.0625],"height":52,"width":64,"animation_speed":0.25},{"line_length":8,"hr_version":{"line_length":8,"frame_count":32,"priority":"high","filename":"__base__/graphics/entity/offshore-pump/hr-offshore-pump_West-shadow.png","scale":0.5,"draw_as_shadow":true,"shift":[-0.09375,0.25],"height":66,"width":172,"animation_speed":0.25},"frame_count":32,"priority":"high","filename":"__base__/graphics/entity/offshore-pump/offshore-pump_West-shadow.png","draw_as_shadow":true,"shift":[-0.125,0.25],"height":34,"width":88,"animation_speed":0.25}]},"east":{"layers":[{"line_length":8,"hr_version":{"line_length":8,"frame_count":32,"priority":"high","filename":"__base__/graphics/entity/offshore-pump/hr-offshore-pump_East.png","scale":0.5,"shift":[0.46875,-0.0625],"height":102,"width":124,"animation_speed":0.25},"frame_count":32,"priority":"high","filename":"__base__/graphics/entity/offshore-pump/offshore-pump_East.png","shift":[0.4375,-0.0625],"height":52,"width":64,"animation_speed":0.25},{"line_length":8,"hr_version":{"line_length":8,"frame_count":32,"priority":"high","filename":"__base__/graphics/entity/offshore-pump/hr-offshore-pump_East-shadow.png","scale":0.5,"draw_as_shadow":true,"shift":[0.84375,0.25],"height":66,"width":180,"animation_speed":0.25},"frame_count":32,"priority":"high","filename":"__base__/graphics/entity/offshore-pump/offshore-pump_East-shadow.png","draw_as_shadow":true,"shift":[0.875,0.25],"height":34,"width":88,"animation_speed":0.25}]},"north":{"layers":[{"line_length":8,"hr_version":{"line_length":8,"frame_count":32,"priority":"high","filename":"__base__/graphics/entity/offshore-pump/hr-offshore-pump_North.png","scale":0.5,"shift":[-0.03125,-0.46875],"height":162,"width":90,"animation_speed":0.25},"frame_count":32,"priority":"high","filename":"__base__/graphics/entity/offshore-pump/offshore-pump_North.png","shift":[-0.0625,-0.5],"height":84,"width":48,"animation_speed":0.25},{"line_length":8,"hr_version":{"line_length":8,"frame_count":32,"priority":"high","filename":"__base__/graphics/entity/offshore-pump/hr-offshore-pump_North-shadow.png","scale":0.5,"draw_as_shadow":true,"shift":[0.40625,-0.21875],"height":134,"width":150,"animation_speed":0.25},"frame_count":32,"priority":"high","filename":"__base__/graphics/entity/offshore-pump/offshore-pump_North-shadow.png","draw_as_shadow":true,"shift":[0.375,-0.25],"height":70,"width":78,"animation_speed":0.25}]},"ignore":true,"south":{"layers":[{"line_length":8,"hr_version":{"line_length":8,"frame_count":32,"priority":"high","filename":"__base__/graphics/entity/offshore-pump/hr-offshore-pump_South.png","scale":0.5,"shift":[-0.03125,0],"height":192,"width":92,"animation_speed":0.25},"frame_count":32,"priority":"high","filename":"__base__/graphics/entity/offshore-pump/offshore-pump_South.png","shift":[-0.0625,0],"height":96,"width":48,"animation_speed":0.25},{"line_length":8,"hr_version":{"line_length":8,"frame_count":32,"priority":"high","filename":"__base__/graphics/entity/offshore-pump/hr-offshore-pump_South-shadow.png","scale":0.5,"draw_as_shadow":true,"shift":[0.46875,0.71875],"height":128,"width":164,"animation_speed":0.25},"frame_count":32,"priority":"high","filename":"__base__/graphics/entity/offshore-pump/offshore-pump_South-shadow.png","draw_as_shadow":true,"shift":[0.5,0.6875],"height":66,"width":80,"animation_speed":0.25}]}}},"rail-chain-signal":{"picture":{"layers":[{"line_length":5,"direction_count":8,"frame_count":5,"priority":"high","filename":"__base__/graphics/entity/rail-chain-signal/rail-chain-signal.png","axially_symmetrical":false,"hr_version":{"line_length":5,"direction_count":8,"frame_count":5,"priority":"high","filename":"__base__/graphics/entity/rail-chain-signal/hr-rail-chain-signal.png","axially_symmetrical":false,"scale":0.5,"height":320,"width":320},"height":160,"width":160},{"blend_mode":"additive","direction_count":8,"frame_count":5,"priority":"low","filename":"__base__/graphics/entity/rail-chain-signal/rail-chain-signal-light.png","draw_as_light":true,"hr_version":{"blend_mode":"additive","direction_count":8,"frame_count":5,"priority":"low","filename":"__base__/graphics/entity/rail-chain-signal/hr-rail-chain-signal-light.png","draw_as_light":true,"scale":0.5,"height":320,"width":320,"line_length":5},"height":160,"width":160,"line_length":5}]}},"steel-furnace":{"picture":{"layers":[{"priority":"high","filename":"__base__/graphics/entity/steel-furnace/steel-furnace.png","hr_version":{"priority":"high","filename":"__base__/graphics/entity/steel-furnace/hr-steel-furnace.png","scale":0.5,"shift":[-0.0390625,0.0625],"height":174,"frame_count":1,"width":171},"shift":[-0.046875,0.046875],"height":87,"frame_count":1,"width":85},{"priority":"high","filename":"__base__/graphics/entity/steel-furnace/steel-furnace-shadow.png","hr_version":{"priority":"high","filename":"__base__/graphics/entity/steel-furnace/hr-steel-furnace-shadow.png","scale":0.5,"shift":[1.2265625,0.3515625],"draw_as_shadow":true,"height":85,"frame_count":1,"width":277},"shift":[1.234375,0.359375],"draw_as_shadow":true,"height":43,"frame_count":1,"width":139}]}},"steel-chest":{"picture":{"layers":[{"priority":"extra-high","filename":"__base__/graphics/entity/steel-chest/steel-chest.png","hr_version":{"priority":"extra-high","filename":"__base__/graphics/entity/steel-chest/hr-steel-chest.png","scale":0.5,"height":80,"shift":[-0.0078125,-0.015625],"width":64},"height":40,"shift":[0,-0.015625],"width":32},{"priority":"extra-high","filename":"__base__/graphics/entity/steel-chest/steel-chest-shadow.png","hr_version":{"priority":"extra-high","filename":"__base__/graphics/entity/steel-chest/hr-steel-chest-shadow.png","scale":0.5,"draw_as_shadow":true,"height":46,"shift":[0.3828125,0.25],"width":110},"draw_as_shadow":true,"height":22,"shift":[0.375,0.234375],"width":56}]}},"fast-inserter":{"picture":{"rot_layers":[{"priority":"extra-high","filename":"__base__/graphics/entity/fast-inserter/fast-inserter-hand-base.png","hr_version":{"priority":"extra-high","filename":"__base__/graphics/entity/fast-inserter/hr-fast-inserter-hand-base.png","scale":0.25,"height":136,"width":32},"height":34,"width":8},{"priority":"extra-high","filename":"__base__/graphics/entity/fast-inserter/fast-inserter-hand-closed.png","hr_version":{"priority":"extra-high","filename":"__base__/graphics/entity/fast-inserter/hr-fast-inserter-hand-closed.png","scale":0.25,"height":164,"width":72},"height":41,"width":18}],"layers":{"priority":"extra-high","filename":"__base__/graphics/entity/fast-inserter/fast-inserter-platform.png","hr_version":{"priority":"extra-high","filename":"__base__/graphics/entity/fast-inserter/hr-fast-inserter-platform.png","scale":0.5,"height":79,"shift":[0.046875,0.203125],"width":105},"height":46,"shift":[0.09375,0],"width":46}}},"logistic-chest-active-provider":{"picture":{"layers":[{"priority":"extra-high","filename":"__base__/graphics/entity/logistic-chest/logistic-chest-active-provider.png","hr_version":{"priority":"extra-high","filename":"__base__/graphics/entity/logistic-chest/hr-logistic-chest-active-provider.png","scale":0.5,"shift":[0,-0.0625],"height":74,"frame_count":7,"width":66},"shift":[0,-0.0625],"height":38,"frame_count":7,"width":34},{"priority":"extra-high","filename":"__base__/graphics/entity/logistic-chest/logistic-chest-shadow.png","hr_version":{"priority":"extra-high","filename":"__base__/graphics/entity/logistic-chest/hr-logistic-chest-shadow.png","scale":0.5,"draw_as_shadow":true,"height":46,"repeat_count":7,"shift":[0.375,0.140625],"width":112},"draw_as_shadow":true,"height":24,"repeat_count":7,"shift":[0.375,0.15625],"width":56}]}},"stack-inserter":{"picture":{"rot_layers":[{"priority":"extra-high","filename":"__base__/graphics/entity/stack-inserter/stack-inserter-hand-base.png","hr_version":{"priority":"extra-high","filename":"__base__/graphics/entity/stack-inserter/hr-stack-inserter-hand-base.png","scale":0.25,"height":136,"width":32},"height":34,"width":8},{"priority":"extra-high","filename":"__base__/graphics/entity/stack-inserter/stack-inserter-hand-closed.png","hr_version":{"priority":"extra-high","filename":"__base__/graphics/entity/stack-inserter/hr-stack-inserter-hand-closed.png","scale":0.25,"height":164,"width":100},"height":41,"width":24}],"layers":{"priority":"extra-high","filename":"__base__/graphics/entity/stack-inserter/stack-inserter-platform.png","hr_version":{"priority":"extra-high","filename":"__base__/graphics/entity/stack-inserter/hr-stack-inserter-platform.png","scale":0.5,"height":79,"shift":[0.046875,0.203125],"width":105},"height":46,"shift":[0.09375,0],"width":46}}},"burner-inserter":{"picture":{"rot_layers":[{"priority":"extra-high","filename":"__base__/graphics/entity/burner-inserter/burner-inserter-hand-base.png","hr_version":{"priority":"extra-high","filename":"__base__/graphics/entity/burner-inserter/hr-burner-inserter-hand-base.png","scale":0.25,"height":136,"width":32},"height":34,"width":8},{"priority":"extra-high","filename":"__base__/graphics/entity/burner-inserter/burner-inserter-hand-closed.png","hr_version":{"priority":"extra-high","filename":"__base__/graphics/entity/burner-inserter/hr-burner-inserter-hand-closed.png","scale":0.25,"height":164,"width":72},"height":41,"width":18}],"layers":{"priority":"extra-high","filename":"__base__/graphics/entity/burner-inserter/burner-inserter-platform.png","hr_version":{"priority":"extra-high","filename":"__base__/graphics/entity/burner-inserter/hr-burner-inserter-platform.png","scale":0.5,"height":79,"shift":[0.046875,0.203125],"width":105},"height":46,"shift":[0.09375,0],"width":46}}},"burner-generator":{"picture":{"west":{"layers":[{"height":128,"filename":"__base__/graphics/entity/steam-engine/steam-engine-H.png","hr_version":{"height":257,"filename":"__base__/graphics/entity/steam-engine/hr-steam-engine-H.png","width":352,"frame_count":32,"line_length":8,"shift":[0.03125,-0.1484375],"scale":0.5},"width":176,"frame_count":32,"shift":[0.03125,-0.15625],"line_length":8},{"height":80,"filename":"__base__/graphics/entity/steam-engine/steam-engine-H-shadow.png","hr_version":{"height":160,"filename":"__base__/graphics/entity/steam-engine/hr-steam-engine-H-shadow.png","width":508,"frame_count":32,"line_length":8,"draw_as_shadow":true,"shift":[1.5,0.75],"scale":0.5},"width":254,"frame_count":32,"line_length":8,"shift":[1.5,0.75],"draw_as_shadow":true}]},"north":{"layers":[{"height":195,"filename":"__base__/graphics/entity/steam-engine/steam-engine-V.png","hr_version":{"height":391,"filename":"__base__/graphics/entity/steam-engine/hr-steam-engine-V.png","width":225,"frame_count":32,"line_length":8,"shift":[0.1484375,-0.1953125],"scale":0.5},"width":112,"frame_count":32,"shift":[0.15625,-0.203125],"line_length":8},{"height":153,"filename":"__base__/graphics/entity/steam-engine/steam-engine-V-shadow.png","hr_version":{"height":307,"filename":"__base__/graphics/entity/steam-engine/hr-steam-engine-V-shadow.png","width":330,"frame_count":32,"line_length":8,"draw_as_shadow":true,"shift":[1.265625,0.2890625],"scale":0.5},"width":165,"frame_count":32,"line_length":8,"shift":[1.265625,0.296875],"draw_as_shadow":true}]},"east":{"layers":[{"height":128,"filename":"__base__/graphics/entity/steam-engine/steam-engine-H.png","hr_version":{"height":257,"filename":"__base__/graphics/entity/steam-engine/hr-steam-engine-H.png","width":352,"frame_count":32,"line_length":8,"shift":[0.03125,-0.1484375],"scale":0.5},"width":176,"frame_count":32,"shift":[0.03125,-0.15625],"line_length":8},{"height":80,"filename":"__base__/graphics/entity/steam-engine/steam-engine-H-shadow.png","hr_version":{"height":160,"filename":"__base__/graphics/entity/steam-engine/hr-steam-engine-H-shadow.png","width":508,"frame_count":32,"line_length":8,"draw_as_shadow":true,"shift":[1.5,0.75],"scale":0.5},"width":254,"frame_count":32,"line_length":8,"shift":[1.5,0.75],"draw_as_shadow":true}]},"south":{"layers":[{"height":195,"filename":"__base__/graphics/entity/steam-engine/steam-engine-V.png","hr_version":{"height":391,"filename":"__base__/graphics/entity/steam-engine/hr-steam-engine-V.png","width":225,"frame_count":32,"line_length":8,"shift":[0.1484375,-0.1953125],"scale":0.5},"width":112,"frame_count":32,"shift":[0.15625,-0.203125],"line_length":8},{"height":153,"filename":"__base__/graphics/entity/steam-engine/steam-engine-V-shadow.png","hr_version":{"height":307,"filename":"__base__/graphics/entity/steam-engine/hr-steam-engine-V-shadow.png","width":330,"frame_count":32,"line_length":8,"draw_as_shadow":true,"shift":[1.265625,0.2890625],"scale":0.5},"width":165,"frame_count":32,"line_length":8,"shift":[1.265625,0.296875],"draw_as_shadow":true}]}}},"player-port":{"picture":{"height":64,"filename":"__base__/graphics/entity/player-port/player-port-animation.png","frame_count":2,"width":64}},"iron-chest":{"picture":{"layers":[{"priority":"extra-high","filename":"__base__/graphics/entity/iron-chest/iron-chest.png","hr_version":{"priority":"extra-high","filename":"__base__/graphics/entity/iron-chest/hr-iron-chest.png","scale":0.5,"height":76,"shift":[-0.015625,-0.015625],"width":66},"height":38,"shift":[0,-0.015625],"width":34},{"priority":"extra-high","filename":"__base__/graphics/entity/iron-chest/iron-chest-shadow.png","hr_version":{"priority":"extra-high","filename":"__base__/graphics/entity/iron-chest/hr-iron-chest-shadow.png","scale":0.5,"draw_as_shadow":true,"height":50,"shift":[0.328125,0.1875],"width":110},"draw_as_shadow":true,"height":26,"shift":[0.3125,0.203125],"width":56}]}},"simple-entity-with-force":{"picture":{"priority":"extra-high","filename":"__base__/graphics/entity/steel-chest/steel-chest.png","height":40,"shift":[-0.34375,0.140625],"width":32}},"oil-refinery":{"picture":{"west":{"layers":[{"x":1011,"y":0,"hr_version":{"x":1158,"y":0,"height":430,"filename":"__base__/graphics/entity/oil-refinery/hr-oil-refinery.png","frame_count":1,"priority":"high","scale":0.5,"shift":[0,-0.234375],"width":386},"height":255,"filename":"__base__/graphics/entity/oil-refinery/oil-refinery.png","frame_count":1,"priority":"high","scale":1,"shift":[2.515625,0.484375],"width":337},{"x":1011,"y":0,"hr_version":{"x":2022,"y":0,"height":426,"filename":"__base__/graphics/entity/oil-refinery/hr-oil-refinery-shadow.png","frame_count":1,"priority":"high","force_hr_shadow":true,"scale":0.5,"draw_as_shadow":true,"shift":[2.578125,0.828125],"width":674},"height":213,"filename":"__base__/graphics/entity/oil-refinery/oil-refinery-shadow.png","frame_count":1,"priority":"high","scale":1,"draw_as_shadow":true,"shift":[2.578125,0.828125],"width":337}]},"north":{"layers":[{"x":0,"y":0,"hr_version":{"x":0,"y":0,"height":430,"filename":"__base__/graphics/entity/oil-refinery/hr-oil-refinery.png","frame_count":1,"priority":"high","scale":0.5,"shift":[0,-0.234375],"width":386},"height":255,"filename":"__base__/graphics/entity/oil-refinery/oil-refinery.png","frame_count":1,"priority":"high","scale":1,"shift":[2.515625,0.484375],"width":337},{"x":0,"y":0,"hr_version":{"x":0,"y":0,"height":426,"filename":"__base__/graphics/entity/oil-refinery/hr-oil-refinery-shadow.png","frame_count":1,"priority":"high","force_hr_shadow":true,"scale":0.5,"draw_as_shadow":true,"shift":[2.578125,0.828125],"width":674},"height":213,"filename":"__base__/graphics/entity/oil-refinery/oil-refinery-shadow.png","frame_count":1,"priority":"high","scale":1,"draw_as_shadow":true,"shift":[2.578125,0.828125],"width":337}]},"east":{"layers":[{"x":337,"y":0,"hr_version":{"x":386,"y":0,"height":430,"filename":"__base__/graphics/entity/oil-refinery/hr-oil-refinery.png","frame_count":1,"priority":"high","scale":0.5,"shift":[0,-0.234375],"width":386},"height":255,"filename":"__base__/graphics/entity/oil-refinery/oil-refinery.png","frame_count":1,"priority":"high","scale":1,"shift":[2.515625,0.484375],"width":337},{"x":337,"y":0,"hr_version":{"x":674,"y":0,"height":426,"filename":"__base__/graphics/entity/oil-refinery/hr-oil-refinery-shadow.png","frame_count":1,"priority":"high","force_hr_shadow":true,"scale":0.5,"draw_as_shadow":true,"shift":[2.578125,0.828125],"width":674},"height":213,"filename":"__base__/graphics/entity/oil-refinery/oil-refinery-shadow.png","frame_count":1,"priority":"high","scale":1,"draw_as_shadow":true,"shift":[2.578125,0.828125],"width":337}]},"south":{"layers":[{"x":674,"y":0,"hr_version":{"x":772,"y":0,"height":430,"filename":"__base__/graphics/entity/oil-refinery/hr-oil-refinery.png","frame_count":1,"priority":"high","scale":0.5,"shift":[0,-0.234375],"width":386},"height":255,"filename":"__base__/graphics/entity/oil-refinery/oil-refinery.png","frame_count":1,"priority":"high","scale":1,"shift":[2.515625,0.484375],"width":337},{"x":674,"y":0,"hr_version":{"x":1348,"y":0,"height":426,"filename":"__base__/graphics/entity/oil-refinery/hr-oil-refinery-shadow.png","frame_count":1,"priority":"high","force_hr_shadow":true,"scale":0.5,"draw_as_shadow":true,"shift":[2.578125,0.828125],"width":674},"height":213,"filename":"__base__/graphics/entity/oil-refinery/oil-refinery-shadow.png","frame_count":1,"priority":"high","scale":1,"draw_as_shadow":true,"shift":[2.578125,0.828125],"width":337}]}}},"assembling-machine-1":{"picture":{"layers":[{"priority":"high","filename":"__base__/graphics/entity/assembling-machine-1/assembling-machine-1.png","hr_version":{"priority":"high","filename":"__base__/graphics/entity/assembling-machine-1/hr-assembling-machine-1.png","scale":0.5,"shift":[0,0.0625],"line_length":8,"height":226,"frame_count":32,"width":214},"shift":[0,0.0625],"line_length":8,"height":114,"frame_count":32,"width":108},{"width":95,"hr_version":{"width":190,"frame_count":1,"priority":"high","filename":"__base__/graphics/entity/assembling-machine-1/hr-assembling-machine-1-shadow.png","scale":0.5,"shift":[0.265625,0.15625],"draw_as_shadow":true,"repeat_count":32,"line_length":1,"height":165},"frame_count":1,"priority":"high","filename":"__base__/graphics/entity/assembling-machine-1/assembling-machine-1-shadow.png","shift":[0.265625,0.171875],"draw_as_shadow":true,"repeat_count":32,"line_length":1,"height":83}]}},"electric-furnace":{"picture":{"layers":[{"priority":"high","filename":"__base__/graphics/entity/electric-furnace/electric-furnace-base.png","hr_version":{"priority":"high","filename":"__base__/graphics/entity/electric-furnace/hr-electric-furnace.png","scale":0.5,"shift":[0.0234375,0.1796875],"height":219,"frame_count":1,"width":239},"shift":[0.421875,0],"height":100,"frame_count":1,"width":129},{"priority":"high","filename":"__base__/graphics/entity/electric-furnace/electric-furnace-shadow.png","hr_version":{"priority":"high","filename":"__base__/graphics/entity/electric-furnace/hr-electric-furnace-shadow.png","scale":0.5,"shift":[0.3515625,0.2421875],"draw_as_shadow":true,"height":171,"frame_count":1,"width":227},"draw_as_shadow":true,"shift":[0.421875,0],"height":100,"frame_count":1,"width":129}]}},"red-chest":{"picture":{"layers":[{"priority":"extra-high","filename":"__base__/graphics/entity/logistic-chest/logistic-chest-passive-provider.png","hr_version":{"priority":"extra-high","filename":"__base__/graphics/entity/logistic-chest/hr-logistic-chest-passive-provider.png","width":66,"frame_count":7,"height":74,"shift":[0,-0.0625],"scale":0.5},"width":34,"frame_count":7,"shift":[0,-0.0625],"height":38},{"priority":"extra-high","filename":"__base__/graphics/entity/logistic-chest/logistic-chest-shadow.png","hr_version":{"priority":"extra-high","filename":"__base__/graphics/entity/logistic-chest/hr-logistic-chest-shadow.png","width":112,"scale":0.5,"repeat_count":7,"height":46,"shift":[0.375,0.140625],"draw_as_shadow":true},"width":56,"height":24,"repeat_count":7,"shift":[0.375,0.15625],"draw_as_shadow":true}]}},"rail-signal":{"picture":{"layers":[{"priority":"high","filename":"__base__/graphics/entity/rail-signal/rail-signal.png","direction_count":8,"hr_version":{"priority":"high","filename":"__base__/graphics/entity/rail-signal/hr-rail-signal.png","direction_count":8,"scale":0.5,"height":192,"frame_count":3,"width":192},"height":96,"frame_count":3,"width":96},{"blend_mode":"additive","direction_count":8,"frame_count":3,"priority":"low","filename":"__base__/graphics/entity/rail-signal/rail-signal-light.png","draw_as_light":true,"hr_version":{"blend_mode":"additive","direction_count":8,"frame_count":3,"priority":"low","filename":"__base__/graphics/entity/rail-signal/hr-rail-signal-light.png","draw_as_light":true,"scale":0.5,"height":192,"width":192},"height":96,"width":96}]}},"nuclear-reactor":{"picture":{"layers":[{"height":158,"filename":"__base__/graphics/entity/nuclear-reactor/reactor.png","hr_version":{"height":318,"filename":"__base__/graphics/entity/nuclear-reactor/hr-reactor.png","scale":0.5,"shift":[-0.15625,-0.21875],"width":302},"shift":[-0.1875,-0.1875],"width":154},{"height":162,"filename":"__base__/graphics/entity/nuclear-reactor/reactor-shadow.png","hr_version":{"height":323,"filename":"__base__/graphics/entity/nuclear-reactor/hr-reactor-shadow.png","draw_as_shadow":true,"scale":0.5,"shift":[1.625,0],"width":525},"draw_as_shadow":true,"shift":[1.625,0],"width":263}]}},"inserter":{"picture":{"rot_layers":[{"priority":"extra-high","filename":"__base__/graphics/entity/inserter/inserter-hand-base.png","hr_version":{"priority":"extra-high","filename":"__base__/graphics/entity/inserter/hr-inserter-hand-base.png","scale":0.25,"height":136,"width":32},"height":33,"width":8},{"priority":"extra-high","filename":"__base__/graphics/entity/inserter/inserter-hand-closed.png","hr_version":{"priority":"extra-high","filename":"__base__/graphics/entity/inserter/hr-inserter-hand-closed.png","scale":0.25,"height":164,"width":72},"height":41,"width":18}],"layers":{"priority":"extra-high","filename":"__base__/graphics/entity/inserter/inserter-platform.png","hr_version":{"priority":"extra-high","filename":"__base__/graphics/entity/inserter/hr-inserter-platform.png","scale":0.5,"height":79,"shift":[0.046875,0.203125],"width":105},"height":46,"shift":[0.09375,0],"width":46}}},"accumulator":{"picture":{"layers":[{"width":66,"hr_version":{"width":130,"shift":[0,-0.34375],"priority":"high","filename":"__base__/graphics/entity/accumulator/hr-accumulator.png","scale":0.5,"animation_speed":0.5,"height":189},"shift":[0,-0.3125],"priority":"high","filename":"__base__/graphics/entity/accumulator/accumulator.png","animation_speed":0.5,"height":94},{"priority":"high","filename":"__base__/graphics/entity/accumulator/accumulator-shadow.png","hr_version":{"priority":"high","filename":"__base__/graphics/entity/accumulator/hr-accumulator-shadow.png","scale":0.5,"draw_as_shadow":true,"height":106,"shift":[0.90625,0.1875],"width":234},"draw_as_shadow":true,"height":54,"shift":[0.875,0.1875],"width":120}]}},"long-handed-inserter":{"picture":{"rot_layers":[{"priority":"extra-high","filename":"__base__/graphics/entity/long-handed-inserter/long-handed-inserter-hand-base.png","hr_version":{"priority":"extra-high","filename":"__base__/graphics/entity/long-handed-inserter/hr-long-handed-inserter-hand-base.png","scale":0.25,"height":136,"width":32},"height":34,"width":8},{"priority":"extra-high","filename":"__base__/graphics/entity/long-handed-inserter/long-handed-inserter-hand-closed.png","hr_version":{"priority":"extra-high","filename":"__base__/graphics/entity/long-handed-inserter/hr-long-handed-inserter-hand-closed.png","scale":0.25,"height":164,"width":72},"height":41,"width":18}],"layers":{"priority":"extra-high","filename":"__base__/graphics/entity/long-handed-inserter/long-handed-inserter-platform.png","hr_version":{"priority":"extra-high","filename":"__base__/graphics/entity/long-handed-inserter/hr-long-handed-inserter-platform.png","scale":0.5,"height":79,"shift":[0.046875,0.203125],"width":105},"height":46,"shift":[0.09375,0],"width":46}}},"assembling-machine-3":{"picture":{"layers":[{"priority":"high","filename":"__base__/graphics/entity/assembling-machine-3/assembling-machine-3.png","hr_version":{"priority":"high","filename":"__base__/graphics/entity/assembling-machine-3/hr-assembling-machine-3.png","scale":0.5,"shift":[0,-0.0234375],"line_length":8,"height":237,"frame_count":32,"width":214},"shift":[0,-0.015625],"line_length":8,"height":119,"frame_count":32,"width":108},{"width":130,"hr_version":{"width":260,"frame_count":32,"priority":"high","filename":"__base__/graphics/entity/assembling-machine-3/hr-assembling-machine-3-shadow.png","scale":0.5,"shift":[0.875,0.125],"draw_as_shadow":true,"line_length":8,"height":162},"frame_count":32,"priority":"high","filename":"__base__/graphics/entity/assembling-machine-3/assembling-machine-3-shadow.png","shift":[0.875,0.125],"draw_as_shadow":true,"line_length":8,"height":82}]}},"simple-entity-with-owner":{"picture":{"layers":[{"priority":"extra-high","filename":"__base__/graphics/entity/iron-chest/iron-chest.png","height":38,"shift":[0,-0.015625],"width":34},{"priority":"extra-high","filename":"__base__/graphics/entity/iron-chest/iron-chest.png","apply_runtime_tint":true,"height":33,"x":18,"shift":[0,-0.015625],"width":10}]}},"solar-panel":{"picture":{"layers":[{"priority":"high","filename":"__base__/graphics/entity/solar-panel/solar-panel.png","hr_version":{"priority":"high","filename":"__base__/graphics/entity/solar-panel/hr-solar-panel.png","scale":0.5,"height":224,"shift":[-0.09375,0.109375],"width":230},"height":112,"shift":[-0.09375,0.09375],"width":116},{"priority":"high","filename":"__base__/graphics/entity/solar-panel/solar-panel-shadow.png","hr_version":{"priority":"high","filename":"__base__/graphics/entity/solar-panel/hr-solar-panel-shadow.png","scale":0.5,"draw_as_shadow":true,"height":180,"shift":[0.296875,0.1875],"width":220},"draw_as_shadow":true,"height":90,"shift":[0.3125,0.1875],"width":112}]}},"stone-furnace":{"picture":{"layers":[{"priority":"extra-high","filename":"__base__/graphics/entity/stone-furnace/stone-furnace.png","hr_version":{"priority":"extra-high","filename":"__base__/graphics/entity/stone-furnace/hr-stone-furnace.png","scale":0.5,"shift":[-0.0078125,0.1875],"height":146,"frame_count":1,"width":151},"shift":[0.453125,0.0625],"height":64,"frame_count":1,"width":81},{"priority":"extra-high","filename":"__base__/graphics/entity/stone-furnace/stone-furnace-shadow.png","hr_version":{"priority":"extra-high","filename":"__base__/graphics/entity/stone-furnace/hr-stone-furnace-shadow.png","scale":0.5,"shift":[0.453125,0.40625],"draw_as_shadow":true,"height":74,"frame_count":1,"width":164},"shift":[0.453125,0.0625],"draw_as_shadow":true,"height":64,"frame_count":1,"width":81}]}},"logistic-chest-passive-provider":{"picture":{"layers":[{"priority":"extra-high","filename":"__base__/graphics/entity/logistic-chest/logistic-chest-passive-provider.png","hr_version":{"priority":"extra-high","filename":"__base__/graphics/entity/logistic-chest/hr-logistic-chest-passive-provider.png","scale":0.5,"shift":[0,-0.0625],"height":74,"frame_count":7,"width":66},"shift":[0,-0.0625],"height":38,"frame_count":7,"width":34},{"priority":"extra-high","filename":"__base__/graphics/entity/logistic-chest/logistic-chest-shadow.png","hr_version":{"priority":"extra-high","filename":"__base__/graphics/entity/logistic-chest/hr-logistic-chest-shadow.png","scale":0.5,"draw_as_shadow":true,"height":46,"repeat_count":7,"shift":[0.375,0.140625],"width":112},"draw_as_shadow":true,"height":24,"repeat_count":7,"shift":[0.375,0.15625],"width":56}]}},"assembling-machine-2":{"picture":{"layers":[{"priority":"high","filename":"__base__/graphics/entity/assembling-machine-2/assembling-machine-2.png","hr_version":{"priority":"high","filename":"__base__/graphics/entity/assembling-machine-2/hr-assembling-machine-2.png","scale":0.5,"shift":[0,0.125],"line_length":8,"height":218,"frame_count":32,"width":214},"shift":[0,0.125],"line_length":8,"height":110,"frame_count":32,"width":108},{"width":98,"hr_version":{"width":196,"frame_count":32,"priority":"high","filename":"__base__/graphics/entity/assembling-machine-2/hr-assembling-machine-2-shadow.png","scale":0.5,"shift":[0.375,0.1484375],"draw_as_shadow":true,"line_length":8,"height":163},"frame_count":32,"priority":"high","filename":"__base__/graphics/entity/assembling-machine-2/assembling-machine-2-shadow.png","shift":[0.375,0.15625],"draw_as_shadow":true,"line_length":8,"height":82}]}},"electric-energy-interface":{"picture":{"layers":[{"width":66,"hr_version":{"width":130,"shift":[0,-0.34375],"priority":"high","filename":"__base__/graphics/entity/accumulator/hr-accumulator.png","scale":0.5,"animation_speed":0.5,"tint":{"b":1,"a":1,"r":1,"g":0.80000000000000004},"height":189},"shift":[0,-0.3125],"priority":"high","filename":"__base__/graphics/entity/accumulator/accumulator.png","animation_speed":0.5,"tint":{"b":1,"a":1,"r":1,"g":0.80000000000000004},"height":94},{"priority":"high","filename":"__base__/graphics/entity/accumulator/accumulator-shadow.png","hr_version":{"priority":"high","filename":"__base__/graphics/entity/accumulator/hr-accumulator-shadow.png","scale":0.5,"draw_as_shadow":true,"height":106,"shift":[0.90625,0.1875],"width":234},"draw_as_shadow":true,"height":54,"shift":[0.875,0.1875],"width":120}]}},"infinity-chest":{"picture":{"layers":[{"priority":"extra-high","filename":"__base__/graphics/entity/infinity-chest/infinity-chest.png","hr_version":{"priority":"extra-high","filename":"__base__/graphics/entity/infinity-chest/hr-infinity-chest.png","scale":0.5,"height":84,"shift":[0,-0.09375],"width":68},"height":42,"shift":[0,-0.09375],"width":34},{"priority":"extra-high","filename":"__base__/graphics/entity/infinity-chest/infinity-chest-shadow.png","hr_version":{"priority":"extra-high","filename":"__base__/graphics/entity/infinity-chest/hr-infinity-chest-shadow.png","scale":0.5,"draw_as_shadow":true,"height":48,"shift":[0.375,0.1875],"width":116},"draw_as_shadow":true,"height":24,"shift":[0.375,0.1875],"width":58}]}},"linked-chest":{"picture":{"layers":[{"priority":"extra-high","filename":"__base__/graphics/entity/linked-chest/linked-chest.png","hr_version":{"priority":"extra-high","filename":"__base__/graphics/entity/linked-chest/hr-linked-chest.png","scale":0.5,"shift":[0,-0.0625],"height":74,"frame_count":7,"width":66},"shift":[0,-0.0625],"height":38,"frame_count":7,"width":34},{"priority":"extra-high","filename":"__base__/graphics/entity/linked-chest/linked-chest-shadow.png","hr_version":{"priority":"extra-high","filename":"__base__/graphics/entity/linked-chest/hr-linked-chest-shadow.png","scale":0.5,"draw_as_shadow":true,"height":46,"repeat_count":7,"shift":[0.375,0.140625],"width":112},"draw_as_shadow":true,"height":24,"repeat_count":7,"shift":[0.375,0.15625],"width":56}]}},"logistic-chest-requester":{"picture":{"layers":[{"priority":"extra-high","filename":"__base__/graphics/entity/logistic-chest/logistic-chest-requester.png","hr_version":{"priority":"extra-high","filename":"__base__/graphics/entity/logistic-chest/hr-logistic-chest-requester.png","scale":0.5,"shift":[0,-0.0625],"height":74,"frame_count":7,"width":66},"shift":[0,-0.0625],"height":38,"frame_count":7,"width":34},{"priority":"extra-high","filename":"__base__/graphics/entity/logistic-chest/logistic-chest-shadow.png","hr_version":{"priority":"extra-high","filename":"__base__/graphics/entity/logistic-chest/hr-logistic-chest-shadow.png","scale":0.5,"draw_as_shadow":true,"height":46,"repeat_count":7,"shift":[0.375,0.140625],"width":112},"draw_as_shadow":true,"height":24,"repeat_count":7,"shift":[0.375,0.15625],"width":56}]}},"logistic-chest-buffer":{"picture":{"layers":[{"priority":"extra-high","filename":"__base__/graphics/entity/logistic-chest/logistic-chest-buffer.png","hr_version":{"priority":"extra-high","filename":"__base__/graphics/entity/logistic-chest/hr-logistic-chest-buffer.png","scale":0.5,"shift":[0,-0.0625],"height":72,"frame_count":7,"width":66},"shift":[0,-0.0625],"height":38,"frame_count":7,"width":34},{"priority":"extra-high","filename":"__base__/graphics/entity/logistic-chest/logistic-chest-shadow.png","hr_version":{"priority":"extra-high","filename":"__base__/graphics/entity/logistic-chest/hr-logistic-chest-shadow.png","scale":0.5,"draw_as_shadow":true,"height":46,"repeat_count":7,"shift":[0.375,0.140625],"width":112},"draw_as_shadow":true,"height":24,"repeat_count":7,"shift":[0.375,0.15625],"width":56}]}},"wooden-chest":{"picture":{"layers":[{"priority":"extra-high","filename":"__base__/graphics/entity/wooden-chest/wooden-chest.png","hr_version":{"priority":"extra-high","filename":"__base__/graphics/entity/wooden-chest/hr-wooden-chest.png","scale":0.5,"height":72,"shift":[0.015625,-0.0625],"width":62},"height":36,"shift":[0.015625,-0.0625],"width":32},{"priority":"extra-high","filename":"__base__/graphics/entity/wooden-chest/wooden-chest-shadow.png","hr_version":{"priority":"extra-high","filename":"__base__/graphics/entity/wooden-chest/hr-wooden-chest-shadow.png","scale":0.5,"draw_as_shadow":true,"height":40,"shift":[0.3125,0.203125],"width":104},"draw_as_shadow":true,"height":20,"shift":[0.3125,0.203125],"width":52}]}},"market":{"picture":{"height":127,"filename":"__base__/graphics/entity/market/market.png","shift":[0.94999999999999996,0.20000000000000001],"width":156}},"blue-chest":{"picture":{"layers":[{"priority":"extra-high","filename":"__base__/graphics/entity/logistic-chest/logistic-chest-requester.png","hr_version":{"priority":"extra-high","filename":"__base__/graphics/entity/logistic-chest/hr-logistic-chest-requester.png","width":66,"frame_count":7,"height":74,"shift":[0,-0.0625],"scale":0.5},"width":34,"frame_count":7,"shift":[0,-0.0625],"height":38},{"priority":"extra-high","filename":"__base__/graphics/entity/logistic-chest/logistic-chest-shadow.png","hr_version":{"priority":"extra-high","filename":"__base__/graphics/entity/logistic-chest/hr-logistic-chest-shadow.png","width":112,"scale":0.5,"repeat_count":7,"height":46,"shift":[0.375,0.140625],"draw_as_shadow":true},"width":56,"height":24,"repeat_count":7,"shift":[0.375,0.15625],"draw_as_shadow":true}]}},"tank":{"picture":{"layers":[{"width":136,"direction_count":64,"frame_count":2,"priority":"low","max_advance":1,"stripes":[{"filename":"__base__/graphics/entity/tank/tank-base-1.png","width_in_frames":2,"height_in_frames":16},{"filename":"__base__/graphics/entity/tank/tank-base-2.png","width_in_frames":2,"height_in_frames":16},{"filename":"__base__/graphics/entity/tank/tank-base-3.png","width_in_frames":2,"height_in_frames":16},{"filename":"__base__/graphics/entity/tank/tank-base-4.png","width_in_frames":2,"height_in_frames":16}],"hr_version":{"width":270,"direction_count":64,"frame_count":2,"priority":"low","max_advance":1,"stripes":[{"filename":"__base__/graphics/entity/tank/hr-tank-base-1.png","width_in_frames":2,"height_in_frames":16},{"filename":"__base__/graphics/entity/tank/hr-tank-base-2.png","width_in_frames":2,"height_in_frames":16},{"filename":"__base__/graphics/entity/tank/hr-tank-base-3.png","width_in_frames":2,"height_in_frames":16},{"filename":"__base__/graphics/entity/tank/hr-tank-base-4.png","width_in_frames":2,"height_in_frames":16}],"scale":0.5,"animation_speed":8,"shift":[0,-0.3125],"height":212},"animation_speed":8,"shift":[0,-0.3125],"height":106},{"width":104,"apply_runtime_tint":true,"frame_count":2,"priority":"low","max_advance":1,"stripes":[{"filename":"__base__/graphics/entity/tank/tank-base-mask-1.png","width_in_frames":1,"height_in_frames":22},{"filename":"__base__/graphics/entity/tank/tank-base-mask-1.png","width_in_frames":1,"height_in_frames":22},{"filename":"__base__/graphics/entity/tank/tank-base-mask-2.png","width_in_frames":1,"height_in_frames":22},{"filename":"__base__/graphics/entity/tank/tank-base-mask-2.png","width_in_frames":1,"height_in_frames":22},{"filename":"__base__/graphics/entity/tank/tank-base-mask-3.png","width_in_frames":1,"height_in_frames":20},{"filename":"__base__/graphics/entity/tank/tank-base-mask-3.png","width_in_frames":1,"height_in_frames":20}],"hr_version":{"width":208,"apply_runtime_tint":true,"frame_count":2,"priority":"low","max_advance":1,"stripes":[{"filename":"__base__/graphics/entity/tank/hr-tank-base-mask-1.png","width_in_frames":1,"height_in_frames":22},{"filename":"__base__/graphics/entity/tank/hr-tank-base-mask-1.png","width_in_frames":1,"height_in_frames":22},{"filename":"__base__/graphics/entity/tank/hr-tank-base-mask-2.png","width_in_frames":1,"height_in_frames":22},{"filename":"__base__/graphics/entity/tank/hr-tank-base-mask-2.png","width_in_frames":1,"height_in_frames":22},{"filename":"__base__/graphics/entity/tank/hr-tank-base-mask-3.png","width_in_frames":1,"height_in_frames":20},{"filename":"__base__/graphics/entity/tank/hr-tank-base-mask-3.png","width_in_frames":1,"height_in_frames":20}],"scale":0.5,"line_length":2,"shift":[0,-0.671875],"direction_count":64,"height":166},"line_length":2,"shift":[0,-0.671875],"direction_count":64,"height":83},{"width":151,"direction_count":64,"frame_count":2,"priority":"low","max_advance":1,"stripes":[{"filename":"__base__/graphics/entity/tank/tank-base-shadow-1.png","width_in_frames":1,"height_in_frames":16},{"filename":"__base__/graphics/entity/tank/tank-base-shadow-1.png","width_in_frames":1,"height_in_frames":16},{"filename":"__base__/graphics/entity/tank/tank-base-shadow-2.png","width_in_frames":1,"height_in_frames":16},{"filename":"__base__/graphics/entity/tank/tank-base-shadow-2.png","width_in_frames":1,"height_in_frames":16},{"filename":"__base__/graphics/entity/tank/tank-base-shadow-3.png","width_in_frames":1,"height_in_frames":16},{"filename":"__base__/graphics/entity/tank/tank-base-shadow-3.png","width_in_frames":1,"height_in_frames":16},{"filename":"__base__/graphics/entity/tank/tank-base-shadow-4.png","width_in_frames":1,"height_in_frames":16},{"filename":"__base__/graphics/entity/tank/tank-base-shadow-4.png","width_in_frames":1,"height_in_frames":16}],"hr_version":{"width":302,"direction_count":64,"frame_count":2,"priority":"low","max_advance":1,"stripes":[{"filename":"__base__/graphics/entity/tank/hr-tank-base-shadow-1.png","width_in_frames":1,"height_in_frames":16},{"filename":"__base__/graphics/entity/tank/hr-tank-base-shadow-1.png","width_in_frames":1,"height_in_frames":16},{"filename":"__base__/graphics/entity/tank/hr-tank-base-shadow-2.png","width_in_frames":1,"height_in_frames":16},{"filename":"__base__/graphics/entity/tank/hr-tank-base-shadow-2.png","width_in_frames":1,"height_in_frames":16},{"filename":"__base__/graphics/entity/tank/hr-tank-base-shadow-3.png","width_in_frames":1,"height_in_frames":16},{"filename":"__base__/graphics/entity/tank/hr-tank-base-shadow-3.png","width_in_frames":1,"height_in_frames":16},{"filename":"__base__/graphics/entity/tank/hr-tank-base-shadow-4.png","width_in_frames":1,"height_in_frames":16},{"filename":"__base__/graphics/entity/tank/hr-tank-base-shadow-4.png","width_in_frames":1,"height_in_frames":16}],"scale":0.5,"shift":[0.703125,0.21875],"draw_as_shadow":true,"height":194},"shift":[0.703125,0.21875],"draw_as_shadow":true,"height":98}]}},"car":{"picture":{"layers":[{"width":102,"direction_count":64,"frame_count":2,"priority":"low","max_advance":0.20000000000000001,"stripes":[{"filename":"__base__/graphics/entity/car/car-1.png","width_in_frames":2,"height_in_frames":22},{"filename":"__base__/graphics/entity/car/car-2.png","width_in_frames":2,"height_in_frames":22},{"filename":"__base__/graphics/entity/car/car-3.png","width_in_frames":2,"height_in_frames":20}],"hr_version":{"width":201,"direction_count":64,"frame_count":2,"priority":"low","scale":0.5,"stripes":[{"filename":"__base__/graphics/entity/car/hr-car-1.png","width_in_frames":2,"height_in_frames":11},{"filename":"__base__/graphics/entity/car/hr-car-2.png","width_in_frames":2,"height_in_frames":11},{"filename":"__base__/graphics/entity/car/hr-car-3.png","width_in_frames":2,"height_in_frames":11},{"filename":"__base__/graphics/entity/car/hr-car-4.png","width_in_frames":2,"height_in_frames":11},{"filename":"__base__/graphics/entity/car/hr-car-5.png","width_in_frames":2,"height_in_frames":11},{"filename":"__base__/graphics/entity/car/hr-car-6.png","width_in_frames":2,"height_in_frames":9}],"max_advance":0.20000000000000001,"animation_speed":8,"shift":[0.0625,-0.09375],"height":172},"animation_speed":8,"shift":[0,-0.1875],"height":86},{"width":100,"apply_runtime_tint":true,"frame_count":2,"priority":"low","max_advance":0.20000000000000001,"stripes":[{"filename":"__base__/graphics/entity/car/car-mask-1.png","width_in_frames":1,"height_in_frames":22},{"filename":"__base__/graphics/entity/car/car-mask-1.png","width_in_frames":1,"height_in_frames":22},{"filename":"__base__/graphics/entity/car/car-mask-2.png","width_in_frames":1,"height_in_frames":22},{"filename":"__base__/graphics/entity/car/car-mask-2.png","width_in_frames":1,"height_in_frames":22},{"filename":"__base__/graphics/entity/car/car-mask-3.png","width_in_frames":1,"height_in_frames":20},{"filename":"__base__/graphics/entity/car/car-mask-3.png","width_in_frames":1,"height_in_frames":20}],"hr_version":{"width":199,"apply_runtime_tint":true,"frame_count":2,"stripes":[{"filename":"__base__/graphics/entity/car/hr-car-mask-1.png","width_in_frames":1,"height_in_frames":13},{"filename":"__base__/graphics/entity/car/hr-car-mask-1.png","width_in_frames":1,"height_in_frames":13},{"filename":"__base__/graphics/entity/car/hr-car-mask-2.png","width_in_frames":1,"height_in_frames":13},{"filename":"__base__/graphics/entity/car/hr-car-mask-2.png","width_in_frames":1,"height_in_frames":13},{"filename":"__base__/graphics/entity/car/hr-car-mask-3.png","width_in_frames":1,"height_in_frames":13},{"filename":"__base__/graphics/entity/car/hr-car-mask-3.png","width_in_frames":1,"height_in_frames":13},{"filename":"__base__/graphics/entity/car/hr-car-mask-4.png","width_in_frames":1,"height_in_frames":13},{"filename":"__base__/graphics/entity/car/hr-car-mask-4.png","width_in_frames":1,"height_in_frames":13},{"filename":"__base__/graphics/entity/car/hr-car-mask-5.png","width_in_frames":1,"height_in_frames":12},{"filename":"__base__/graphics/entity/car/hr-car-mask-5.png","width_in_frames":1,"height_in_frames":12}],"priority":"low","scale":0.5,"axially_symmetrical":false,"line_length":1,"shift":[0.0625,-0.078125],"max_advance":0.20000000000000001,"direction_count":64,"height":147},"shift":[0,-0.171875],"line_length":2,"direction_count":64,"height":75},{"width":114,"direction_count":64,"frame_count":2,"priority":"low","max_advance":0.20000000000000001,"stripes":[{"filename":"__base__/graphics/entity/car/car-shadow-1.png","width_in_frames":1,"height_in_frames":22},{"filename":"__base__/graphics/entity/car/car-shadow-1.png","width_in_frames":1,"height_in_frames":22},{"filename":"__base__/graphics/entity/car/car-shadow-2.png","width_in_frames":1,"height_in_frames":22},{"filename":"__base__/graphics/entity/car/car-shadow-2.png","width_in_frames":1,"height_in_frames":22},{"filename":"__base__/graphics/entity/car/car-shadow-3.png","width_in_frames":1,"height_in_frames":20},{"filename":"__base__/graphics/entity/car/car-shadow-3.png","width_in_frames":1,"height_in_frames":20}],"shift":[0.28125,0.25],"draw_as_shadow":true,"height":76}]}},"filter-inserter":{"picture":{"rot_layers":[{"priority":"extra-high","filename":"__base__/graphics/entity/filter-inserter/filter-inserter-hand-base.png","hr_version":{"priority":"extra-high","filename":"__base__/graphics/entity/filter-inserter/hr-filter-inserter-hand-base.png","scale":0.25,"height":136,"width":32},"height":34,"width":8},{"priority":"extra-high","filename":"__base__/graphics/entity/filter-inserter/filter-inserter-hand-closed.png","hr_version":{"priority":"extra-high","filename":"__base__/graphics/entity/filter-inserter/hr-filter-inserter-hand-closed.png","scale":0.25,"height":164,"width":72},"height":41,"width":18}],"layers":{"priority":"extra-high","filename":"__base__/graphics/entity/filter-inserter/filter-inserter-platform.png","hr_version":{"priority":"extra-high","filename":"__base__/graphics/entity/filter-inserter/hr-filter-inserter-platform.png","scale":0.5,"height":79,"shift":[0.046875,0.203125],"width":105},"height":46,"shift":[0.09375,0],"width":46}}},"heat-interface":{"picture":{"height":32,"filename":"__base__/graphics/icons/heat-interface.png","hr_version":{"height":64,"filename":"__base__/graphics/icons/heat-interface.png","width":64,"scale":0.5,"flags":["no-crop"]},"width":32,"x":64,"flags":["no-crop"]}},"logistic-chest-storage":{"picture":{"layers":[{"priority":"extra-high","filename":"__base__/graphics/entity/logistic-chest/logistic-chest-storage.png","hr_version":{"priority":"extra-high","filename":"__base__/graphics/entity/logistic-chest/hr-logistic-chest-storage.png","scale":0.5,"shift":[0,-0.0625],"height":74,"frame_count":7,"width":66},"shift":[0,-0.0625],"height":38,"frame_count":7,"width":34},{"priority":"extra-high","filename":"__base__/graphics/entity/logistic-chest/logistic-chest-shadow.png","hr_version":{"priority":"extra-high","filename":"__base__/graphics/entity/logistic-chest/hr-logistic-chest-shadow.png","scale":0.5,"draw_as_shadow":true,"height":46,"repeat_count":7,"shift":[0.375,0.140625],"width":112},"draw_as_shadow":true,"height":24,"repeat_count":7,"shift":[0.375,0.15625],"width":56}]}},"stack-filter-inserter":{"picture":{"rot_layers":[{"priority":"extra-high","filename":"__base__/graphics/entity/stack-filter-inserter/stack-filter-inserter-hand-base.png","hr_version":{"priority":"extra-high","filename":"__base__/graphics/entity/stack-filter-inserter/hr-stack-filter-inserter-hand-base.png","scale":0.25,"height":136,"width":32},"height":34,"width":8},{"priority":"extra-high","filename":"__base__/graphics/entity/stack-filter-inserter/stack-filter-inserter-hand-closed.png","hr_version":{"priority":"extra-high","filename":"__base__/graphics/entity/stack-filter-inserter/hr-stack-filter-inserter-hand-closed.png","scale":0.25,"height":164,"width":100},"height":41,"width":24}],"layers":{"priority":"extra-high","filename":"__base__/graphics/entity/stack-filter-inserter/stack-filter-inserter-platform.png","hr_version":{"priority":"extra-high","filename":"__base__/graphics/entity/stack-filter-inserter/hr-stack-filter-inserter-platform.png","scale":0.5,"height":79,"shift":[0.046875,0.203125],"width":105},"height":46,"shift":[0.09375,0],"width":46}}}}